wwpdb/utils/testing/CreateRWTree.py
wwpdb/utils/testing/Features.py
wwpdb/utils/testing/SiteConfigSetup.py
wwpdb/utils/testing/__init__.py
wwpdb/utils/testing/py.typed
wwpdb.utils.testing-0.19.2.dist-info/LICENSE
wwpdb.utils.testing-0.19.2.dist-info/METADATA
wwpdb.utils.testing-0.19.2.dist-info/WHEEL
wwpdb.utils.testing-0.19.2.dist-info/top_level.txt
wwpdb.utils.testing-0.19.2.dist-info/RECORD
