Metadata-Version: 2.1
Name: wwpdb.utils.testing
Version: 0.19.2
Summary: wwPDB Python DB Schema Utilities
Author-email: Ezra Peisach <ezra.peisach@rcsb.org>
License: Apache 2.0
Project-URL: Homepage, https://github,com/wwpdb/py-wwpdb_utils_testing
Classifier: Intended Audience :: Developers
Classifier: Natural Language :: English
Classifier: License :: OSI Approved :: Apache Software License
Classifier: Programming Language :: Python
Classifier: Programming Language :: Python :: 3
Classifier: Programming Language :: Python :: 3.6
Classifier: Programming Language :: Python :: 3.7
Classifier: Programming Language :: Python :: 3.8
Requires-Python: >=3.6
License-File: LICENSE
